[
  {
    "title": "Abivax Pushes Back On Takeover Rumors",
    "link": "https://app.moby.co/home/news/news-abivax-pushes-back-on-takeover-rumors?utm_source=yahoo_finance&utm_medium=rss",
    "publisher": "Moby",
    "date": "2026-03-12T18:55:51Z",
    "type": "STORY"
  },
  {
    "title": "Sector Update: Health Care Stocks Lower in Afternoon Trading",
    "link": "https://finance.yahoo.com/news/sector-health-care-stocks-lower-180038248.html",
    "publisher": "MT Newswires",
    "date": "2026-03-12T18:00:38Z",
    "type": "STORY"
  },
  {
    "title": "Retirees Are Quietly Collecting Income From London’s Biggest Dividend Payers",
    "link": "https://247wallst.com/investing/2026/03/12/retirees-are-quietly-collecting-income-from-londons-biggest-dividend-payers/",
    "publisher": "24/7 Wall St.",
    "date": "2026-03-12T13:22:48Z",
    "type": "STORY"
  },
  {
    "title": "Compugen Ltd. (CGEN) Reports Q4 Revenue of $67.3 Million vs. $1.5 Million Last Year",
    "link": "https://finance.yahoo.com/news/compugen-ltd-cgen-reports-q4-073804754.html",
    "publisher": "Insider Monkey",
    "date": "2026-03-12T07:38:04Z",
    "type": "STORY"
  },
  {
    "title": "Poolbeg Pharma adds CAR-T therapy expert to scientific advisory board",
    "link": "https://www.proactiveinvestors.com/companies/news/1088771/poolbeg-pharma-adds-car-t-therapy-expert-to-scientific-advisory-board-1088771.html",
    "publisher": "Proactive",
    "date": "2026-03-12T07:33:00Z",
    "type": "STORY"
  },
  {
    "title": "Morgan Stanley Sees Double-Digit EPS Growth for AstraZeneca PLC (AZN)",
    "link": "https://finance.yahoo.com/news/morgan-stanley-sees-double-digit-063059179.html",
    "publisher": "Insider Monkey",
    "date": "2026-03-12T06:30:59Z",
    "type": "STORY"
  },
  {
    "title": "Relay Therapeutics (RLAY) Soars 5.4%: Is Further Upside Left in the Stock?",
    "link": "https://finance.yahoo.com/news/relay-therapeutics-rlay-soars-5-130300518.html",
    "publisher": "Zacks",
    "date": "2026-03-11T13:03:00Z",
    "type": "STORY"
  },
  {
    "title": "Is AstraZeneca (LSE:AZN) Still Attractive After Recent Share Price Pullback?",
    "link": "https://finance.yahoo.com/news/astrazeneca-lse-azn-still-attractive-031218514.html",
    "publisher": "Simply Wall St.",
    "date": "2026-03-10T03:12:18Z",
    "type": "STORY"
  },
  {
    "title": "AstraZeneca Oncology Updates Prompt Fresh Look At Valuation And Growth Potential",
    "link": "https://finance.yahoo.com/news/astrazeneca-oncology-updates-prompt-fresh-020645856.html",
    "publisher": "Simply Wall St.",
    "date": "2026-03-10T02:06:45Z",
    "type": "STORY"
  },
  {
    "title": "Factbox-Global drugmakers rush to boost US presence as tariff threat looms",
    "link": "https://finance.yahoo.com/news/factbox-global-drugmakers-rush-boost-174250083.html",
    "publisher": "Reuters",
    "date": "2026-03-09T17:42:50Z",
    "type": "STORY"
  }
]