[
  {
    "title": "Oil Rises in Choppy Session as Saudi Supplies Hit By Attacks",
    "link": "https://finance.yahoo.com/news/oil-rises-biggest-drop-since-001648111.html",
    "publisher": "Bloomberg",
    "date": "2026-04-09T20:11:49Z",
    "type": "STORY"
  },
  {
    "title": "How CIBC’s New US$1.25 Billion Covered Bond Issue (TSX:CM) Has Changed Its Investment Story",
    "link": "https://finance.yahoo.com/markets/stocks/articles/cibc-us-1-25-billion-111044762.html",
    "publisher": "Simply Wall St.",
    "date": "2026-04-09T11:10:44Z",
    "type": "STORY"
  },
  {
    "title": "CIBC (CM) Just Made A Quiet Move Into A Fast-Growing Corner Of Finance",
    "link": "https://finance.yahoo.com/markets/stocks/articles/cibc-cm-just-made-quiet-194512520.html",
    "publisher": "Insider Monkey",
    "date": "2026-04-08T19:45:12Z",
    "type": "STORY"
  },
  {
    "title": "CIBC on Highlander Silver's Portfolio Update",
    "link": "https://finance.yahoo.com/markets/stocks/articles/cibc-highlander-silver-apos-portfolio-181110641.html",
    "publisher": "MT Newswires",
    "date": "2026-04-08T18:11:10Z",
    "type": "STORY"
  },
  {
    "title": "CIBC Previews Aviation Sector's Q1, Trims Air Canada Price Target to $22.00",
    "link": "https://finance.yahoo.com/sectors/technology/articles/cibc-previews-aviation-sector-apos-170208688.html",
    "publisher": "MT Newswires",
    "date": "2026-04-08T17:02:08Z",
    "type": "STORY"
  },
  {
    "title": "CIBC Lowers Price Target On Boyd Group Services By C$5, But Keeps Outperformer Rating",
    "link": "https://finance.yahoo.com/markets/stocks/articles/cibc-lowers-price-target-boyd-183240019.html",
    "publisher": "MT Newswires",
    "date": "2026-04-07T18:32:40Z",
    "type": "STORY"
  },
  {
    "title": "How The Kneat.com (TSX:KSI) Story Is Shifting As Analysts Reset Price Targets",
    "link": "https://finance.yahoo.com/markets/stocks/articles/kneat-com-tsx-ksi-story-070956772.html",
    "publisher": "Simply Wall St.",
    "date": "2026-04-06T07:09:56Z",
    "type": "STORY"
  },
  {
    "title": "CIBC On the Week Ahead In Canada Economics",
    "link": "https://finance.yahoo.com/economy/articles/cibc-week-ahead-canada-economics-182527555.html",
    "publisher": "MT Newswires",
    "date": "2026-04-02T18:25:27Z",
    "type": "STORY"
  },
  {
    "title": "CIBC Provides Q1 Freight Transportation Earnings Preview",
    "link": "https://finance.yahoo.com/markets/stocks/articles/cibc-provides-q1-freight-transportation-174252331.html",
    "publisher": "MT Newswires",
    "date": "2026-04-02T17:42:52Z",
    "type": "STORY"
  },
  {
    "title": "CIBC Confirms Outperformer Rating on Cargojet and Raises Target to $122",
    "link": "https://finance.yahoo.com/markets/stocks/articles/cibc-confirms-outperformer-rating-cargojet-155857232.html",
    "publisher": "MT Newswires",
    "date": "2026-04-02T15:58:57Z",
    "type": "STORY"
  }
]