[
  {
    "title": "Poste Italiane (BIT:PST) Valuation Check After Strong Multi‑Year Share Price Rally",
    "link": "https://finance.yahoo.com/news/poste-italiane-bit-pst-valuation-130634804.html",
    "publisher": "Simply Wall St.",
    "date": "2025-12-23T13:06:34Z",
    "type": "STORY"
  },
  {
    "title": "Has Poste Italiane’s 57% Rally in 2025 Already Priced In Its Transformation Story?",
    "link": "https://finance.yahoo.com/news/poste-italiane-57-rally-2025-050829471.html",
    "publisher": "Simply Wall St.",
    "date": "2025-12-23T05:08:29Z",
    "type": "STORY"
  },
  {
    "title": "Italy’s Treasury agrees to sell digital payments unit PagoPA to Poste Italiane",
    "link": "https://www.electronicpaymentsinternational.com/news/pagopa-poste-italiane/",
    "publisher": "Electronic Payments",
    "date": "2025-12-22T11:33:13Z",
    "type": "STORY"
  },
  {
    "title": "Italy sells digital payment unit PagoPA to Poste, state mint for up to 500 million euros",
    "link": "https://finance.yahoo.com/news/italy-sells-digital-payment-unit-172337835.html",
    "publisher": "Reuters",
    "date": "2025-12-19T17:23:37Z",
    "type": "STORY"
  },
  {
    "title": "Poste Italiane SpA (PITAF) Q3 2025 Earnings Call Highlights: Record Revenue and Strategic ...",
    "link": "https://finance.yahoo.com/news/poste-italiane-spa-pitaf-q3-170046226.html",
    "publisher": "GuruFocus.com",
    "date": "2025-11-13T17:00:46Z",
    "type": "STORY"
  },
  {
    "title": "Poste Italiane considers digital identity fee, analysts see potential 100 million euro profit boost",
    "link": "https://finance.yahoo.com/news/poste-italiane-considers-digital-identity-123153739.html",
    "publisher": "Reuters",
    "date": "2025-09-26T12:31:53Z",
    "type": "STORY"
  },
  {
    "title": "Poste Italiane (BIT:PST): Exploring Valuation After a Period of Strong Share Performance",
    "link": "https://finance.yahoo.com/news/poste-italiane-bit-pst-exploring-112859620.html",
    "publisher": "Simply Wall St.",
    "date": "2025-09-24T11:28:59Z",
    "type": "STORY"
  },
  {
    "title": "Poste Italiane SpA (FRA:7PI) Q2 2025 Earnings Call Highlights: Record Revenue and Profit Growth ...",
    "link": "https://finance.yahoo.com/news/poste-italiane-spa-fra-7pi-070751823.html",
    "publisher": "GuruFocus.com",
    "date": "2025-07-23T07:07:51Z",
    "type": "STORY"
  },
  {
    "title": "Italy asks Poste, state mint to revive talks over PagoPA deal",
    "link": "https://finance.yahoo.com/news/italy-asks-poste-state-mint-111826841.html",
    "publisher": "Reuters",
    "date": "2025-07-16T11:18:26Z",
    "type": "STORY"
  },
  {
    "title": "Poste Italiane SpA (PITAF) Q1 2025 Earnings Call Highlights: Record Revenue and Strategic ...",
    "link": "https://finance.yahoo.com/news/poste-italiane-spa-pitaf-q1-072603684.html",
    "publisher": "GuruFocus.com",
    "date": "2025-05-09T07:26:03Z",
    "type": "STORY"
  }
]