[
  {
    "title": "Poste’s TIM Bid Is Really a Bet on Rebuilding Italy Inc",
    "link": "https://app.moby.co/home/news/news-postes-tim-bid-is-really-a-bet-on-rebuilding-italy-inc?utm_source=yahoo_finance&utm_medium=rss",
    "publisher": "Moby",
    "date": "2026-03-23T18:11:32Z",
    "type": "STORY"
  },
  {
    "title": "Italy’s Postal Service Makes $12.50 Billion Bid for Telecom Italia",
    "link": "https://www.wsj.com/business/deals/poste-italiane-unveils-12-50-billion-offer-for-telecom-italia-5cb73a87?siteid=yhoof2&yptr=yahoo",
    "publisher": "The Wall Street Journal",
    "date": "2026-03-23T12:53:00Z",
    "type": "STORY"
  },
  {
    "title": "Monte Dei Paschi Board Ousts CEO Lovaglio",
    "link": "https://www.wsj.com/finance/banking/monte-dei-paschi-board-ousts-ceo-lovaglio-1b6900cb?siteid=yhoof2&yptr=yahoo",
    "publisher": "The Wall Street Journal",
    "date": "2026-03-05T07:19:00Z",
    "type": "STORY"
  },
  {
    "title": "Poste Italiane (BIT:PST) Valuation Check After Strong Multi‑Year Share Price Rally",
    "link": "https://finance.yahoo.com/news/poste-italiane-bit-pst-valuation-130634804.html",
    "publisher": "Simply Wall St.",
    "date": "2025-12-23T13:06:34Z",
    "type": "STORY"
  },
  {
    "title": "Has Poste Italiane’s 57% Rally in 2025 Already Priced In Its Transformation Story?",
    "link": "https://finance.yahoo.com/news/poste-italiane-57-rally-2025-050829471.html",
    "publisher": "Simply Wall St.",
    "date": "2025-12-23T05:08:29Z",
    "type": "STORY"
  },
  {
    "title": "Italy’s Treasury agrees to sell digital payments unit PagoPA to Poste Italiane",
    "link": "https://www.electronicpaymentsinternational.com/news/pagopa-poste-italiane/",
    "publisher": "Electronic Payments",
    "date": "2025-12-22T11:33:13Z",
    "type": "STORY"
  },
  {
    "title": "Italy sells digital payment unit PagoPA to Poste, state mint for up to 500 million euros",
    "link": "https://finance.yahoo.com/news/italy-sells-digital-payment-unit-172337835.html",
    "publisher": "Reuters",
    "date": "2025-12-19T17:23:37Z",
    "type": "STORY"
  },
  {
    "title": "Poste Italiane SpA (PITAF) Q3 2025 Earnings Call Highlights: Record Revenue and Strategic ...",
    "link": "https://finance.yahoo.com/news/poste-italiane-spa-pitaf-q3-170046226.html",
    "publisher": "GuruFocus.com",
    "date": "2025-11-13T17:00:46Z",
    "type": "STORY"
  },
  {
    "title": "Poste Italiane considers digital identity fee, analysts see potential 100 million euro profit boost",
    "link": "https://finance.yahoo.com/news/poste-italiane-considers-digital-identity-123153739.html",
    "publisher": "Reuters",
    "date": "2025-09-26T12:31:53Z",
    "type": "STORY"
  },
  {
    "title": "Poste Italiane (BIT:PST): Exploring Valuation After a Period of Strong Share Performance",
    "link": "https://finance.yahoo.com/news/poste-italiane-bit-pst-exploring-112859620.html",
    "publisher": "Simply Wall St.",
    "date": "2025-09-24T11:28:59Z",
    "type": "STORY"
  }
]